textstructparser/__init__.py
textstructparser/main.py
textstructparser/prompts.py
textstructparser-2025.12.20202423.dist-info/METADATA
textstructparser-2025.12.20202423.dist-info/WHEEL
textstructparser-2025.12.20202423.dist-info/top_level.txt
textstructparser-2025.12.20202423.dist-info/RECORD
