Metadata-Version: 2.4
Name: textstructparser
Version: 2025.12.20202423
Summary: A new package designed to parse and structure information from unstructured text. It takes textual input and utilizes advanced language models with pattern matching to extract specific data points, en
Author-email: textstructparser <hi@eugene.plus>
License: MIT
Project-URL: Homepage, https://github.com/chigwell/textstructparser
Requires-Python: >=3.9
Requires-Dist: langchain-llm7>=0.0.0
Requires-Dist: llmatch-messages>=0.0.0
Requires-Dist: langchain-core>=0.3.0
